FPfda/__init__.py
FPfda/mypr.py
skfirsttry-0.0.1.dist-info/LICENSE
skfirsttry-0.0.1.dist-info/METADATA
skfirsttry-0.0.1.dist-info/WHEEL
skfirsttry-0.0.1.dist-info/top_level.txt
skfirsttry-0.0.1.dist-info/RECORD
